{"Itbt": 0, "Pace": 0.0294871, "Depth": 10, "Degree": 6, "RPSTime": 0.525071, "FBBTTime": 0, "OBBTTime": 0, "TotalTime": 3.28871, "Iterations": 48, "LinearTime": 0.646007, "LowerBound": 116.085, "TimeVector": [0.538348, 0.609038, 0.670962, 0.735464, 0.804281, 0.86011, 0.913142, 0.977352, 1.03479, 1.09289, 1.14707, 1.19883, 1.24762, 1.29756, 1.34915, 1.41175, 1.46476, 1.52005, 1.57195, 1.6272, 1.6747, 1.73205, 1.78588, 1.84076, 1.89332, 1.94829, 2.00791, 2.06669, 2.13293, 2.18655, 2.24308, 2.31048, 2.36619, 2.422, 2.47645, 2.53999, 2.60077, 2.66105, 2.72768, 2.78353, 2.84894, 2.911, 2.97335, 3.03854, 3.1006, 3.16018, 3.22287, 6.51158], "UpperBound": 116.201, "rootBTTime": 0, "LowerBounds": {"1": 84.2963, "2": 89.4573, "3": 92.3146, "4": 93.0621, "5": 95.3602, "6": 97.5033, "7": 99.5995, "8": 99.8599, "9": 101.121, "10": 103.462, "11": 104.619, "12": 106.317, "13": 106.976, "14": 107.381, "15": 108.266, "16": 108.419, "17": 108.744, "18": 109.872, "19": 110.488, "20": 110.843, "21": 110.895, "22": 111.966, "23": 112.259, "24": 112.289, "25": 112.791, "26": 112.93, "27": 113.282, "28": 113.482, "29": 113.643, "30": 113.712, "31": 114.017, "32": 114.213, "33": 114.323, "34": 114.407, "35": 114.559, "36": 114.75, "37": 114.823, "38": 114.986, "39": 115.095, "40": 115.168, "41": 115.24, "42": 115.254, "43": 115.37, "44": 115.73, "45": 115.845, "46": 115.921, "47": 115.929, "48": 116.085}, "SolveResult": 0, "UpperBounds": {"1": 116.201}, "MaxQueueSize": 10, "VisitedNodes": 97, "BranchingVars": [2, 1, 0, 0, 1, 3, 0, 5, 0, 0, 0, 0, 4, 3, 5, 5, 0, 0, 0, 4, 0, 2, 5, 0, 5, 4, 4, 0, 2, 0, 5, 2, 2, 0, 0, 0, 1, 0, 1, 2, 1, 1, 1, 1, 0, 1, 1, 4], "NonLinearTime": 0.213734, "OptimalityGap": 0.115882, "BranchingRules": ["eigen_cen_alternative_rel", "eigen_cen_alternative_rel", "eigen_cen_alternative_rel", "eigen_cen_alternative_rel", "eigen_cen_alternative_rel", "eigen_cen_alternative_rel", "eigen_cen_alternative_rel", "eigen_cen_alternative_rel", "eigen_cen_alternative_rel", "eigen_cen_alternative_rel", "eigen_cen_alternative_rel", "eigen_cen_alternative_rel", "eigen_cen_alternative_rel", "eigen_cen_alternative_rel", "eigen_cen_alternative_rel", "sum_rescaled_var_range_weighted_rel", "eigen_cen_alternative_rel", "eigen_cen_alternative_rel", "eigen_cen_alternative_rel", "eigen_cen_alternative_rel", "eigen_cen_alternative_rel", "eigen_cen_alternative_rel", "eigen_cen_alternative_rel", "eigen_cen_alternative_rel", "sum_rescaled_var_range_weighted_rel", "eigen_cen_alternative_rel", "eigen_cen_alternative_rel", "eigen_cen_alternative_rel", "eigen_cen_alternative_rel", "eigen_cen_alternative_rel", "eigen_cen_alternative_rel", "eigen_cen_alternative_rel", "eigen_cen_alternative_rel", "eigen_cen_alternative_rel", "eigen_cen_alternative_rel", "eigen_cen_alternative_rel", "eigen_cen_alternative_rel", "eigen_cen_alternative_rel", "eigen_cen_alternative_rel", "eigen_cen_alternative_rel", "eigen_cen_alternative_rel", "eigen_cen_alternative_rel", "eigen_cen_alternative_rel", "eigen_cen_alternative_rel", "eigen_cen_alternative_rel", "eigen_cen_alternative_rel", "eigen_cen_alternative_rel", "eigen_cen_alternative_rel"], "LBImprovements": [5.161, 2.8573, 7.2849, 2.29814, 13.0587, 2.35669, 7.78102, 3.60192, 5.19558, 5.28215, 7.66953, 5.64921, 9.11378, 0.885868, 1.60551, 4.51135, 5.66313, 6.95764, 6.05722, 1.41605, 17.3138, 8.99788, 4.56003, 8.91691, 6.25336, 0.781905, 0.199329, 0.731232, 1.10721, 0.610701, 4.5235, 0.773587, 1.40744, 7.27928, 0.609727, 0.344847, 1.02158, 0.254031, 0.834277, 2.10483, 0.833301, 0.963061, 0.868573, 0.694722, 0.24052, 0.591188, 0.192567, 0.0196898], "InfeasibleNodes": 3, "ElapsedTimeCoeffs": 0, "LinearizationTime": 0.000674135, "NumberOfVariables": 6, "CallsToLinearSolver": 97, "LinearGenerationTime": 0.11628, "SDPCutsGenerationTime": 0, "CallsToNonLinearSolver": 9, "StrongBranchingExtraTime": 2.35132, "ElapsedTimeWeightedCoeffs": 0, "NodesDiscardedByFathoming": 0, "NodesDiscardedByTolerance": 46, "BoundFactorConstraintsTime": 0.0461591, "ElapsedTimeVarsInConstraints": 0.000016021, "meanBTRelativeChangeRootNode": 0, "NumberOfBoundFactorConstraints": 82, "NumberOfLAPACKConvergenceFailures": 0, "NumberOfRLTVariablesAfterLinearization": 53}