{"Itbt": 0, "Pace": 0.269387, "Depth": 3, "Degree": 2, "RPSTime": 0.00215304, "FBBTTime": 0, "OBBTTime": 0, "TotalTime": 0.326016, "Iterations": 3, "LinearTime": 0.179364, "LowerBound": -1.6, "TimeVector": [0.288732, 0.300994, 0.62701], "UpperBound": -1.6, "rootBTTime": 0, "LowerBounds": {"1": -2.8, "2": -2.6, "3": -1.6}, "SolveResult": 0, "UpperBounds": {"1": 0.00000000500674, "2": -1.6}, "MaxQueueSize": 1, "VisitedNodes": 7, "BranchingVars": [0, 1, 1], "NonLinearTime": 0.142708, "OptimalityGap": 0.00000000501052, "BranchingRules": ["sum_dual_weighted_plus1_rel", "sum_dual_weighted_plus1_rel", "sum_dual_weighted_plus1_rel"], "LBImprovements": [0.2, 0.9, 0.1], "InfeasibleNodes": 0, "ElapsedTimeCoeffs": 0, "LinearizationTime": 0.000005479, "NumberOfVariables": 2, "CallsToLinearSolver": 7, "LinearGenerationTime": 0.0697973, "SDPCutsGenerationTime": 0, "CallsToNonLinearSolver": 4, "StrongBranchingExtraTime": 0.00248207, "ElapsedTimeWeightedCoeffs": 0, "NodesDiscardedByFathoming": 2, "NodesDiscardedByTolerance": 2, "BoundFactorConstraintsTime": 0.000061481, "ElapsedTimeVarsInConstraints": 0.000004477, "meanBTRelativeChangeRootNode": 0, "NumberOfBoundFactorConstraints": 6, "NumberOfLAPACKConvergenceFailures": 0, "NumberOfRLTVariablesAfterLinearization": 2}