{"Itbt": 0, "Pace": 0.00210357, "Depth": 3, "Degree": 2, "RPSTime": 0.00171797, "FBBTTime": 0, "OBBTTime": 0, "TotalTime": 0.210359, "Iterations": 3, "LinearTime": 0.036845, "LowerBound": -450, "TimeVector": [0.16429, 0.17924, 0.389599], "UpperBound": -450, "rootBTTime": 0, "LowerBounds": {"1": -550, "2": -518.75, "3": -450}, "SolveResult": 0, "UpperBounds": {"1": -450}, "MaxQueueSize": 1, "VisitedNodes": 7, "BranchingVars": [0, 4, 2], "NonLinearTime": 0.171789, "OptimalityGap": 0.0000280955, "BranchingRules": ["sum_rescaled_var_range_weighted", "sum_rescaled_var_range_weighted", "sum_rescaled_var_range_weighted"], "LBImprovements": [31.25, 35.4167, 33.3333], "InfeasibleNodes": 0, "ElapsedTimeCoeffs": 0, "LinearizationTime": 0.000026148, "NumberOfVariables": 13, "CallsToLinearSolver": 7, "LinearGenerationTime": 0.0170918, "SDPCutsGenerationTime": 0, "CallsToNonLinearSolver": 4, "StrongBranchingExtraTime": 0, "ElapsedTimeWeightedCoeffs": 0, "NodesDiscardedByFathoming": 0, "NodesDiscardedByTolerance": 4, "BoundFactorConstraintsTime": 0.000157984, "ElapsedTimeVarsInConstraints": 0, "meanBTRelativeChangeRootNode": 0, "NumberOfBoundFactorConstraints": 24, "NumberOfLAPACKConvergenceFailures": 0, "NumberOfRLTVariablesAfterLinearization": 6}