{"Itbt": 0, "Pace": 0.0000835136, "Depth": 9, "Degree": 8, "RPSTime": 0.048895, "FBBTTime": 0, "OBBTTime": 0, "TotalTime": 0.675116, "Iterations": 9, "LinearTime": 0.443378, "LowerBound": -0.0572336, "TimeVector": [0.557348, 0.573315, 0.589488, 0.604515, 0.620496, 0.627218, 0.63394, 0.648314, 0.649277, 0.660643, 1.33576], "UpperBound": 0.00000000000545697, "rootBTTime": 0, "LowerBounds": {"1": -7661.68, "2": -1226.19, "3": -265.448, "4": -72.2798, "5": -20.9853, "6": -6.57028, "7": -3.99899, "8": -0.348517, "9": -0.0572336}, "SolveResult": 100, "UpperBounds": {"1": 0.00000000000545697}, "MaxQueueSize": 3, "VisitedNodes": 19, "BranchingVars": [0, 0, 0, 0, 0, 0, 0, 0, 0], "NonLinearTime": 0.171409, "OptimalityGap": 0.0572336, "BranchingRules": ["sum_dual_weighted_plus1_rel", "sum_dual_weighted_plus1_rel", "sum_dual_weighted_plus1_rel", "sum_dual_weighted_plus1_rel", "sum_dual_weighted_plus1_rel", "sum_dual_weighted_plus1_rel", "sum_dual_weighted_plus1_rel", "sum_dual_weighted_plus1_rel", "sum_dual_weighted_plus1_rel"], "LBImprovements": [6435.49, 960.74, 193.168, 51.2944, 14.4151, 2.57129, 2.51574, 1.13473, 0.295648], "InfeasibleNodes": 1, "ElapsedTimeCoeffs": 0, "LinearizationTime": 0.000313793, "NumberOfVariables": 1, "CallsToLinearSolver": 19, "LinearGenerationTime": 0.105305, "SDPCutsGenerationTime": 0, "CallsToNonLinearSolver": 8, "StrongBranchingExtraTime": 0.0352658, "ElapsedTimeWeightedCoeffs": 0, "NodesDiscardedByFathoming": 0, "NodesDiscardedByTolerance": 7, "BoundFactorConstraintsTime": 0.0173831, "ElapsedTimeVarsInConstraints": 0.000004707, "meanBTRelativeChangeRootNode": 0, "NumberOfBoundFactorConstraints": 9, "NumberOfLAPACKConvergenceFailures": 0, "NumberOfRLTVariablesAfterLinearization": 7}