{"Itbt": 0, "Pace": 0.00684515, "Depth": 4, "Degree": 4, "RPSTime": 0.00805479, "FBBTTime": 0, "OBBTTime": 0, "TotalTime": 0.114189, "Iterations": 5, "LinearTime": 0.0382961, "LowerBound": -30.2893, "TimeVector": [0.035348, 0.0523238, 0.0688735, 0.0880366, 0.202226], "UpperBound": -30.2893, "rootBTTime": 0, "LowerBounds": {"1": -46.9701, "2": -35.4629, "3": -33.1471, "4": -32.8183, "5": -30.2893}, "SolveResult": 0, "UpperBounds": {"1": -30.2893}, "MaxQueueSize": 2, "VisitedNodes": 11, "BranchingVars": [5, 7, 3, 3, 7], "NonLinearTime": 0.0678301, "OptimalityGap": 0.0000000225568, "BranchingRules": ["eigen_cen_alternative_rel", "eigen_cen_alternative_rel", "eigen_cen_alternative_rel", "eigen_cen_alternative_rel", "eigen_cen_alternative_rel"], "LBImprovements": [11.5072, 2.31579, 2.59261, 6.18971, 0.265225], "InfeasibleNodes": 0, "ElapsedTimeCoeffs": 0, "LinearizationTime": 0.000704335, "NumberOfVariables": 12, "CallsToLinearSolver": 11, "LinearGenerationTime": 0.00459639, "SDPCutsGenerationTime": 0, "CallsToNonLinearSolver": 6, "StrongBranchingExtraTime": 0, "ElapsedTimeWeightedCoeffs": 0, "NodesDiscardedByFathoming": 0, "NodesDiscardedByTolerance": 6, "BoundFactorConstraintsTime": 0.00277101, "ElapsedTimeVarsInConstraints": 0, "meanBTRelativeChangeRootNode": 0, "NumberOfBoundFactorConstraints": 106, "NumberOfLAPACKConvergenceFailures": 0, "NumberOfRLTVariablesAfterLinearization": 65}