{"Itbt": 0, "Pace": 0.0204663, "Depth": 10, "Degree": 4, "RPSTime": 0.391753, "FBBTTime": 0, "OBBTTime": 0, "TotalTime": 2.81426, "Iterations": 32, "LinearTime": 0.354137, "LowerBound": -287.006, "TimeVector": [0.391992, 0.476753, 0.564403, 0.651315, 0.737322, 0.809526, 0.891936, 0.976738, 1.04785, 1.12148, 1.19264, 1.26994, 1.34656, 1.4246, 1.4988, 1.58782, 1.65759, 1.73612, 1.814, 1.88928, 1.96356, 2.03207, 2.10585, 2.1862, 2.25959, 2.34383, 2.41594, 2.49316, 2.57201, 2.64295, 2.71708, 5.53134], "UpperBound": -286.72, "rootBTTime": 0, "LowerBounds": {"1": -315.872, "2": -308.091, "3": -304.007, "4": -300.071, "5": -297.716, "6": -294.536, "7": -293.775, "8": -292.33, "9": -291.913, "10": -291.377, "11": -291.184, "12": -289.909, "13": -289.756, "14": -289.735, "15": -289.716, "16": -289.606, "17": -289.556, "18": -289.502, "19": -288.772, "20": -288.743, "21": -288.413, "22": -288.29, "23": -288.21, "24": -288.089, "25": -287.967, "26": -287.809, "27": -287.795, "28": -287.601, "29": -287.511, "30": -287.416, "31": -287.412, "32": -287.006}, "SolveResult": 0, "UpperBounds": {"1": -283.871, "2": -286.72}, "MaxQueueSize": 10, "VisitedNodes": 65, "BranchingVars": [3, 9, 3, 3, 2, 2, 2, 5, 5, 2, 2, 2, 5, 5, 3, 7, 3, 5, 3, 2, 3, 2, 3, 5, 5, 2, 3, 2, 5, 3, 3, 3], "NonLinearTime": 0.200064, "OptimalityGap": 0.285408, "BranchingRules": ["eigen_cen_alternative_rel", "eigen_cen_alternative_rel", "eigen_cen_alternative_rel", "eigen_cen_alternative_rel", "eigen_cen_alternative_rel", "eigen_cen_alternative_rel", "eigen_cen_alternative_rel", "eigen_cen_alternative_rel", "eigen_cen_alternative_rel", "eigen_cen_alternative_rel", "eigen_cen_alternative_rel", "eigen_cen_alternative_rel", "eigen_cen_alternative_rel", "eigen_cen_alternative_rel", "eigen_cen_alternative_rel", "eigen_cen_alternative_rel", "eigen_cen_alternative_rel", "eigen_cen_alternative_rel", "eigen_cen_alternative_rel", "eigen_cen_alternative_rel", "eigen_cen_alternative_rel", "eigen_cen_alternative_rel", "eigen_cen_alternative_rel", "eigen_cen_alternative_rel", "eigen_cen_alternative_rel", "eigen_cen_alternative_rel", "eigen_cen_alternative_rel", "eigen_cen_alternative_rel", "eigen_cen_alternative_rel", "eigen_cen_alternative_rel", "eigen_cen_alternative_rel", "eigen_cen_alternative_rel"], "LBImprovements": [7.78099, 4.08417, 6.29073, 7.74072, 3.18086, 2.6228, 4.04029, 0.952996, 0.729314, 1.66077, 1.62799, 3.43803, 1.34307, 2.13347, 1.74904, 0.833922, 1.26545, 1.69307, 2.21647, 3.95214, 1.91345, 0.495198, 1.72243, 2.76208, 0.555058, 1.95108, 0.789691, 0.96959, 0.412895, 0.782348, 0.747328, 1.86122], "InfeasibleNodes": 0, "ElapsedTimeCoeffs": 0, "LinearizationTime": 0.000564737, "NumberOfVariables": 12, "CallsToLinearSolver": 65, "LinearGenerationTime": 0.080381, "SDPCutsGenerationTime": 0, "CallsToNonLinearSolver": 9, "StrongBranchingExtraTime": 2.22345, "ElapsedTimeWeightedCoeffs": 0, "NodesDiscardedByFathoming": 0, "NodesDiscardedByTolerance": 33, "BoundFactorConstraintsTime": 0.0147461, "ElapsedTimeVarsInConstraints": 0.000025078, "meanBTRelativeChangeRootNode": 0, "NumberOfBoundFactorConstraints": 100, "NumberOfLAPACKConvergenceFailures": 0, "NumberOfRLTVariablesAfterLinearization": 57}