{"Itbt": 0, "Pace": 0.222808, "Depth": 11, "Degree": 4, "RPSTime": 1358.39, "FBBTTime": 0, "OBBTTime": 0, "TotalTime": 6359.78, "Iterations": 116, "LinearTime": 376.697, "LowerBound": 36175.3, "TimeVector": [39.4404, 78.4954, 117.285, 158.53, 193.787, 243.626, 279.91, 357.223, 402.46, 445.407, 507.809, 554.177, 620.261, 688.864, 758.969, 798.266, 851.492, 890.685, 943.017, 996.572, 1052.14, 1133.29, 1188.2, 1234.78, 1302.59, 1344.8, 1386.29, 1458.32, 1521.37, 1565.8, 1604.55, 1643.49, 1703.35, 1744.19, 1834.87, 1875.35, 1913.64, 1955.78, 1998.48, 2040.99, 2079.46, 2139.72, 2179.63, 2273.91, 2323.7, 2364.12, 2447.99, 2513.86, 2577.93, 2662.93, 2734.9, 2818.37, 2881.98, 2920.25, 2968.69, 3012.2, 3054.25, 3094.13, 3132.88, 3230.65, 3266.39, 3302.23, 3341.55, 3377.05, 3437.91, 3482.16, 3528.02, 3563.37, 3626.81, 3670.13, 3744.7, 3793.98, 3892.31, 3954.94, 4015.5, 4093.31, 4134.01, 4181.05, 4272.13, 4309.86, 4373.17, 4416.1, 4479.49, 4521.85, 4564.08, 4604.99, 4642.14, 4765.22, 4809.94, 4851.29, 4916.5, 5017.3, 5070.38, 5114.54, 5158.16, 5197.1, 5262.77, 5301.46, 5350.06, 5491.13, 5536.95, 5584.91, 5628, 5675.04, 5713.68, 5762.52, 5807.51, 5853.62, 5941.56, 5978.2, 6053.06, 6131.03, 6240.9, 6283.18, 6322.19, 6359.78], "UpperBound": 36210, "rootBTTime": 0, "LowerBounds": {"1": 33999.2, "2": 34735.8, "3": 34929.1, "4": 35264, "5": 35267.7, "6": 35363.5, "7": 35396.6, "8": 35538.2, "9": 35622.3, "10": 35684.7, "11": 35685.1, "12": 35711.7, "13": 35717.7, "14": 35754.9, "15": 35795.1, "16": 35795.1, "17": 35832, "18": 35850.6, "19": 35853.4, "20": 35863.8, "21": 35874, "22": 35880.6, "23": 35894.1, "24": 35899.1, "25": 35914.3, "26": 35926.2, "27": 35955.3, "28": 35963, "29": 35967.2, "30": 35971.7, "31": 35976.1, "32": 35988.1, "33": 35989.8, "34": 36000.6, "35": 36001, "36": 36017.9, "37": 36022.3, "38": 36024, "39": 36026.5, "40": 36032, "41": 36039.2, "42": 36049.4, "43": 36050.1, "44": 36051.2, "45": 36059.9, "46": 36060.5, "47": 36064.7, "48": 36065.9, "49": 36068.6, "50": 36072.2, "51": 36075.3, "52": 36076.7, "53": 36080.4, "54": 36082.1, "55": 36082.2, "56": 36084.7, "57": 36085, "58": 36087.5, "59": 36089.6, "60": 36092.8, "61": 36094.7, "62": 36095.1, "63": 36097.1, "64": 36097.6, "65": 36100.9, "66": 36105.1, "67": 36106.7, "68": 36106.8, "69": 36108.5, "70": 36108.8, "71": 36111.4, "72": 36113.8, "73": 36122.6, "74": 36122.7, "75": 36124.9, "76": 36126.4, "77": 36127.2, "78": 36131.1, "79": 36132.5, "80": 36133.2, "81": 36135.3, "82": 36138.8, "83": 36140.5, "84": 36143.4, "85": 36143.6, "86": 36146.2, "87": 36146.5, "88": 36148.6, "89": 36148.7, "90": 36149.3, "91": 36149.8, "92": 36151.1, "93": 36153.7, "94": 36156.7, "95": 36157, "96": 36161.5, "97": 36161.5, "98": 36162.3, "99": 36162.7, "100": 36162.8, "101": 36163, "102": 36165.5, "103": 36166.3, "104": 36166.4, "105": 36167.1, "106": 36167.3, "107": 36168.2, "108": 36170.1, "109": 36170.6, "110": 36170.7, "111": 36171.4, "112": 36171.8, "113": 36172.2, "114": 36172.9, "115": 36173.5, "116": 36175.3}, "SolveResult": 0, "UpperBounds": {"1": 36210}, "MaxQueueSize": 41, "VisitedNodes": 233, "BranchingVars": [0, 7, 7, 3, 9, 1, 1, 3, 4, 4, 1, 4, 4, 8, 1, 9, 1, 1, 5, 9, 2, 4, 3, 5, 5, 3, 1, 5, 2, 9, 3, 3, 2, 3, 1, 0, 0, 2, 0, 1, 3, 3, 2, 3, 8, 9, 1, 3, 8, 8, 9, 3, 5, 2, 2, 2, 3, 2, 3, 1, 1, 2, 2, 2, 1, 2, 2, 2, 4, 4, 4, 2, 0, 9, 8, 2, 2, 0, 1, 1, 9, 1, 9, 2, 0, 1, 7, 9, 9, 1, 1, 4, 0, 0, 0, 1, 2, 7, 9, 9, 1, 9, 7, 8, 0, 9, 7, 7, 1, 2, 4, 3, 9, 7, 1, 7], "NonLinearTime": 0.718387, "OptimalityGap": 34.6365, "BranchingRules": ["sum_dual_weighted_plus1_rel", "sum_dual_weighted_plus1_rel", "sum_dual_weighted_plus1_rel", "sum_dual_weighted_plus1_rel", "sum_dual_weighted_plus1_rel", "sum_dual_weighted_plus1_rel", "sum_dual_weighted_plus1_rel", "sum_dual_weighted_plus1_rel", "sum_dual_weighted_plus1_rel", "sum_dual_weighted_plus1_rel", "sum_dual_weighted_plus1_rel", "sum_dual_weighted_plus1_rel", "sum_dual_weighted_plus1_rel", "sum_dual_weighted_plus1_rel", "sum_dual_weighted_plus1_rel", "sum_dual_weighted_plus1_rel", "sum_dual_weighted_plus1_rel", "sum_dual_weighted_plus1_rel", "sum_dual_weighted_plus1_rel", "sum_dual_weighted_plus1_rel", "sum_dual_weighted_plus1_rel", "sum_dual_weighted_plus1_rel", "sum_dual_weighted_plus1_rel", "sum_dual_weighted_plus1_rel", "sum_dual_weighted_plus1_rel", "sum_dual_weighted_plus1_rel", "sum_dual_weighted_plus1_rel", "sum_dual_weighted_plus1_rel", "sum_dual_weighted_plus1_rel", "sum_dual_weighted_plus1_rel", "sum_dual_weighted_plus1_rel", "sum_dual_weighted_plus1_rel", "sum_dual_weighted_plus1_rel", "sum_dual_weighted_plus1_rel", "sum_dual_weighted_plus1_rel", "sum_dual_weighted_plus1_rel", "sum_dual_weighted_plus1_rel", "sum_dual_weighted_plus1_rel", "sum_dual_weighted_plus1_rel", "sum_dual_weighted_plus1_rel", "sum_dual_weighted_plus1_rel", "sum_dual_weighted_plus1_rel", "sum_dual_weighted_plus1_rel", "sum_dual_weighted_plus1_rel", "sum_dual_weighted_plus1_rel", "sum_dual_weighted_plus1_rel", "sum_dual_weighted_plus1_rel", "sum_dual_weighted_plus1_rel", "sum_dual_weighted_plus1_rel", "sum_dual_weighted_plus1_rel", "sum_dual_weighted_plus1_rel", "sum_dual_weighted_plus1_rel", "sum_dual_weighted_plus1_rel", "sum_dual_weighted_plus1_rel", "sum_dual_weighted_plus1_rel", "sum_dual_weighted_plus1_rel", "sum_dual_weighted_plus1_rel", "sum_dual_weighted_plus1_rel", "sum_dual_weighted_plus1_rel", "sum_dual_weighted_plus1_rel", "sum_dual_weighted_plus1_rel", "sum_dual_weighted_plus1_rel", "sum_dual_weighted_plus1_rel", "sum_dual_weighted_plus1_rel", "sum_dual_weighted_plus1_rel", "sum_dual_weighted_plus1_rel", "sum_dual_weighted_plus1_rel", "sum_dual_weighted_plus1_rel", "sum_dual_weighted_plus1_rel", "sum_dual_weighted_plus1_rel", "sum_dual_weighted_plus1_rel", "sum_dual_weighted_plus1_rel", "sum_dual_weighted_plus1_rel", "sum_dual_weighted_plus1_rel", "sum_dual_weighted_plus1_rel", "sum_dual_weighted_plus1_rel", "sum_dual_weighted_plus1_rel", "sum_dual_weighted_plus1_rel", "sum_dual_weighted_plus1_rel", "sum_dual_weighted_plus1_rel", "sum_dual_weighted_plus1_rel", "sum_dual_weighted_plus1_rel", "sum_dual_weighted_plus1_rel", "sum_dual_weighted_plus1_rel", "sum_dual_weighted_plus1_rel", "sum_dual_weighted_plus1_rel", "sum_dual_weighted_plus1_rel", "sum_dual_weighted_plus1_rel", "sum_dual_weighted_plus1_rel", "sum_dual_weighted_plus1_rel", "sum_dual_weighted_plus1_rel", "sum_dual_weighted_plus1_rel", "sum_dual_weighted_plus1_rel", "sum_dual_weighted_plus1_rel", "sum_dual_weighted_plus1_rel", "sum_dual_weighted_plus1_rel", "sum_dual_weighted_plus1_rel", "sum_dual_weighted_plus1_rel", "sum_dual_weighted_plus1_rel", "sum_dual_weighted_plus1_rel", "sum_dual_weighted_plus1_rel", "sum_dual_weighted_plus1_rel", "sum_dual_weighted_plus1_rel", "sum_dual_weighted_plus1_rel", "sum_dual_weighted_plus1_rel", "sum_dual_weighted_plus1_rel", "sum_dual_weighted_plus1_rel", "sum_dual_weighted_plus1_rel", "sum_dual_weighted_plus1_rel", "sum_dual_weighted_plus1_rel", "sum_dual_weighted_plus1_rel", "sum_dual_weighted_plus1_rel", "sum_dual_weighted_plus1_rel", "sum_dual_weighted_plus1_rel", "sum_dual_weighted_plus1_rel", "sum_dual_weighted_plus1_rel"], "LBImprovements": [736.531, 528.194, 434.336, 421.112, 270.508, 354.205, 288.081, 216.617, 228.263, 179.103, 277.925, 83.4545, 333.573, 40.2332, 99.0008, 131.094, 292.911, 188.569, 231.589, 124.387, 185.878, 194.666, 95.7377, 72.6015, 150.367, 29.1133, 62.572, 185.605, 98.6744, 142.083, 46.1241, 61.9924, 118.93, 31.4266, 107.432, 69.5737, 72.4128, 185.162, 78.5961, 52.6447, 171.066, 32.7648, 80.9844, 120.929, 62.8065, 183.759, 162.663, 66.5543, 260.79, 90.6573, 47.2729, 63.7733, 115.165, 64.4285, 103.412, 69.041, 269.771, 51.3628, 149.787, 146.841, 48.7277, 66.4169, 65.9041, 35.55, 154.893, 63.1239, 60.5705, 49.9409, 105.154, 133.165, 66.6826, 64.5214, 48.0124, 157.409, 106.152, 83.7964, 78.9264, 45.6743, 38.977, 49.7817, 173.368, 26.7177, 35.8227, 67.5598, 51.1786, 31.9347, 26.9473, 76.8354, 17.6694, 60.0402, 58.9928, 11.5612, 40.8985, 59.8865, 40.444, 63.8829, 108.697, 26.3529, 34.7824, 73.6474, 42.7335, 18.26, 17.1508, 146.026, 50.7515, 20.1393, 35.0945, 33.4001, 40.1815, 45.684, 44.8582, 6.38312, 65.1442, 32.3422, 33.7168, 28.4568], "InfeasibleNodes": 0, "ElapsedTimeCoeffs": 0, "LinearizationTime": 2.57929, "NumberOfVariables": 12, "CallsToLinearSolver": 233, "LinearGenerationTime": 16.55, "SDPCutsGenerationTime": 0, "CallsToNonLinearSolver": 10, "StrongBranchingExtraTime": 5874.92, "ElapsedTimeWeightedCoeffs": 0, "NodesDiscardedByFathoming": 0, "NodesDiscardedByTolerance": 117, "BoundFactorConstraintsTime": 99.711, "ElapsedTimeVarsInConstraints": 0.000898194, "meanBTRelativeChangeRootNode": 0, "NumberOfBoundFactorConstraints": 17550, "NumberOfLAPACKConvergenceFailures": 0, "NumberOfRLTVariablesAfterLinearization": 1807}